{
  "title": "Gzip File Explorer",
  "directive": "gzip-file-explorer",
  "description": "Decompress and explore the contents of Gzip (.gz, .tgz) compressed files directly in your browser.",
  "inputConfig": {
    "acceptsMimeTypes": ["application/gzip", "application/x-gzip"],
    "stateFiles": [
      {
        "stateKey": "selectedGzipFileId"
      }
    ]
  },
  "outputConfig": {
    "transferableContent": [
      {
        "dataType": "reference",
        "stateKey": "decompressedFileId"
      }
    ]
  },
  "tags": ["gzip", "decompress", "file", "compression", "archive", "tgz"],
  "includeInSitemap": true,
  "status": "stable"
}