{
  "title": "Songbook",
  "description": "Create, manage, and view your personal collection of songs with lyrics and chords. Upload existing files or add songs manually.",
  "directive": "songbook",
  "inputConfig": {
    "acceptsMimeTypes": [
      "application/vnd.oet.songdata+json",
      "text/plain",
      "application/x-chordpro"
    ],
    "stateFiles": "none"
  },
  "outputConfig": {
    "transferableContent": [
      {
        "dataType": "reference",
        "stateKey": "selectedItemIds"
      }
    ]
  },
  "includeInSitemap": true,
  "status": "stable"
}
